yophonebot/YoTypes.py
yophonebot/__init__.py
yophonebot/bot.py
yophonebot/exceptions.py
yophonebot/utils.py
yophonebot-0.1.7.dist-info/LICENSE
yophonebot-0.1.7.dist-info/METADATA
yophonebot-0.1.7.dist-info/WHEEL
yophonebot-0.1.7.dist-info/top_level.txt
yophonebot-0.1.7.dist-info/RECORD
